reddit_data_collector/__init__.py
reddit_data_collector/exceptions.py
reddit_data_collector/io.py
reddit_data_collector/reddit_data_collector.py
reddit_data_collector-1.1.0.dist-info/LICENSE
reddit_data_collector-1.1.0.dist-info/METADATA
reddit_data_collector-1.1.0.dist-info/WHEEL
reddit_data_collector-1.1.0.dist-info/top_level.txt
reddit_data_collector-1.1.0.dist-info/RECORD
