Metadata-Version: 2.1
Name: reddit-data-collector
Version: 1.1.0
Summary: A Python package that is used to download posts and comments from Reddit.
Home-page: https://github.com/nicovandenhooff/reddit-data-collector
Author: Nico Van den Hooff
License: MIT
Project-URL: Examples, https://github.com/nicovandenhooff/reddit-data-collector/tree/main/examples
Project-URL: Bug Reports, https://github.com/nicovandenhooff/reddit-data-collector/issues
Project-URL: Source, https://github.com/nicovandenhooff/reddit-data-collector
Keywords: reddit,data science,machine learning,data collection,text
Platform: UNKNOWN
Classifier: Intended Audience :: Science/Research
Classifier: License :: OSI Approved :: MIT License
Classifier: Operating System :: OS Independent
Classifier: Programming Language :: Python :: 3
Classifier: Topic :: Text Processing
License-File: LICENSE
Requires-Dist: pandas (>=1.3.5)
Requires-Dist: praw (>=7.5.0)
Requires-Dist: tqdm (>=4.62.3)
